{
  "id": "NAME-001",
  "category": "all",
  "severity": "Minor",
  "title": "Follow IFS naming standards",
  "description": "Ensure objects, variables, cursors, and entity sets conform to IFS naming rules.",
  "recommendation": "Check naming guidelines. Cursors should start with 'c_', local variables with 'v_' or 'l_', and entity sets should be plural.",
  "pattern": "(cursor\\s+(?!c_)\\w+|entityset\\s+name=\"(?!.*s\"|.*ies\"|.*Service\")[^\"]+\")",
  "alertOnMissing": false,
  "approved": true,
  "source": "builtin",
  "classification": "IFS_AQS"
}